pycobertura/__init__.py
pycobertura/__main__.py
pycobertura/cli.py
pycobertura/cobertura.py
pycobertura/filesystem.py
pycobertura/reporters.py
pycobertura/utils.py
pycobertura/templates/__init__.py
pycobertura/templates/filters.py
pycobertura/templates/html-delta.jinja2
pycobertura/templates/html.jinja2
pycobertura/templates/macro.source.jinja2
pycobertura/templates/normalize.css
pycobertura/templates/skeleton.css
pycobertura-4.1.0.dist-info/licenses/LICENSE
pycobertura-4.1.0.dist-info/METADATA
pycobertura-4.1.0.dist-info/WHEEL
pycobertura-4.1.0.dist-info/entry_points.txt
pycobertura-4.1.0.dist-info/top_level.txt
pycobertura-4.1.0.dist-info/RECORD
