Metadata-Version: 2.4
Name: pycobertura
Version: 4.1.0
Summary: "A Cobertura coverage parser that can diff reports and show coverage progress."
Home-page: https://github.com/aconrad/pycobertura
Author: "Alex Conrad"
Author-email: "alexandre.conrad@gmail.com"
Maintainer: "Alex Conrad"
Maintainer-email: "alexandre.conrad@gmail.com"
Keywords: "cobertura coverage diff report parser parse xml"
Classifier: Topic :: Software Development :: Libraries :: Python Modules
Classifier: License :: OSI Approved :: MIT License
Classifier: Natural Language :: English
Classifier: Operating System :: OS Independent
Classifier: Programming Language :: Python
Classifier: Programming Language :: Python :: 3
Classifier: Programming Language :: Python :: 3 :: Only
Classifier: Programming Language :: Python :: 3.7
Classifier: Programming Language :: Python :: 3.8
Classifier: Programming Language :: Python :: 3.9
Requires-Python: >=3.7
License-File: LICENSE
Requires-Dist: click>=4.0
Requires-Dist: jinja2
Requires-Dist: lxml
Requires-Dist: tabulate
Requires-Dist: ruamel.yaml
Dynamic: license-file
